jupyter_toc/__init__.py
jupyter_toc-1.1.2.dist-info/LICENSE
jupyter_toc-1.1.2.dist-info/METADATA
jupyter_toc-1.1.2.dist-info/WHEEL
jupyter_toc-1.1.2.dist-info/entry_points.txt
jupyter_toc-1.1.2.dist-info/top_level.txt
jupyter_toc-1.1.2.dist-info/RECORD
