Metadata-Version: 2.1
Name: jupyter-toc
Version: 1.1.2
Summary: A Python package for generating a table of contents for Jupyter notebooks
Home-page: https://github.com/heyodai/jupyter-toc
Author: Odai Athamneh
Author-email: heyodai@gmail.com
License: UNKNOWN
Platform: UNKNOWN
License-File: LICENSE
Requires-Dist: nbformat
Requires-Dist: nbconvert
